{"frames": {

"BGIdle":
{
	"frame": {"x":10,"y":10,"w":121,"h":620},
	"rotated": false,
	"trimmed": false,
	"spriteSourceSize": {"x":0,"y":0,"w":121,"h":620},
	"sourceSize": {"w":121,"h":620}
},
"BGHappy":
{
	"frame": {"x":141,"y":10,"w":121,"h":620},
	"rotated": false,
	"trimmed": false,
	"spriteSourceSize": {"x":0,"y":0,"w":121,"h":620},
	"sourceSize": {"w":121,"h":620}
},
"BGSad":
{
	"frame": {"x":272,"y":10,"w":121,"h":620},
	"rotated": false,
	"trimmed": false,
	"spriteSourceSize": {"x":0,"y":0,"w":121,"h":620},
	"sourceSize": {"w":121,"h":620}
}},
"meta": {
	"app": "Adobe Animate",
	"version": "15.2.1.95",
	"image": "Object_BG5.png",
	"format": "RGBA8888",
	"size": {"w":512,"h":1024},
	"scale": "1"
}
}
